randstr_plus/__init__.py
randstr_plus/randstr_plus.py
randstr_plus-0.0.2.dist-info/LICENSE
randstr_plus-0.0.2.dist-info/WHEEL
randstr_plus-0.0.2.dist-info/METADATA
randstr_plus-0.0.2.dist-info/RECORD
