Metadata-Version: 2.1
Name: randstr-plus
Version: 0.0.2
Summary: A more flexible string generator
Home-page: https://github.com/garytyler/randstr-plus
License: MIT
Author: Gary Tyler
Author-email: mail@garytyler.com
Requires-Python: >=3.6,<4.0
Classifier: Environment :: Plugins
Classifier: Framework :: Pytest
Classifier: License :: OSI Approved :: MIT License
Classifier: Programming Language :: Python :: 3
Classifier: Programming Language :: Python :: 3.6
Classifier: Programming Language :: Python :: 3.7
Classifier: Programming Language :: Python :: 3.8
Classifier: Programming Language :: Python :: 3.9
Classifier: Topic :: Software Development :: Testing
Classifier: Topic :: System :: Networking
Project-URL: Repository, https://github.com/garytyler/randstr-plus
